qkd_tandem/__init__.py
qkd_tandem/actors/__init__.py
qkd_tandem/actors/alice.py
qkd_tandem/actors/bob.py
qkd_tandem/actors/eve.py
qkd_tandem/analytics/__init__.py
qkd_tandem/analytics/metrics.py
qkd_tandem/analytics/plots.py
qkd_tandem/channels/__init__.py
qkd_tandem/channels/bb84.py
qkd_tandem/channels/kill_switch.py
qkd_tandem/cli/__init__.py
qkd_tandem/cli/run.py
qkd_tandem/cli/simulation.py
qkd_tandem/experiments/__init__.py
qkd_tandem/experiments/config.py
qkd_tandem/noise/__init__.py
qkd_tandem/noise/model.py
qkd_tandem/sabotage/__init__.py
qkd_tandem/sabotage/basic.py
qkd_tandem/sabotage/star_qft.py
qkd_tandem/tests/test_bb84.py
qkd_tandem/tests/test_kill_switch.py
qkd_tandem-0.2.0.dist-info/licenses/LICENSE
qkd_tandem-0.2.0.dist-info/METADATA
qkd_tandem-0.2.0.dist-info/WHEEL
qkd_tandem-0.2.0.dist-info/entry_points.txt
qkd_tandem-0.2.0.dist-info/top_level.txt
qkd_tandem-0.2.0.dist-info/RECORD
