Metadata-Version: 2.4
Name: qkd_tandem
Version: 0.2.0
Summary: Quantum Kill Switch with trielliptic commitments
License: # MITx License
License-File: LICENSE
Requires-Dist: qiskit
Requires-Dist: qiskit-aer
Requires-Dist: matplotlib
Requires-Dist: numpy
Requires-Dist: blake3
Requires-Dist: cryptography
Dynamic: license-file
